[{"isbn":"683096189-0","count":70,"price":20.61},
{"isbn":"495225040-7","count":67,"price":53.24},
{"isbn":"361128335-5","count":89,"price":89.13},
{"isbn":"827035804-5","count":154,"price":73.08},
{"isbn":"894646987-0","count":346,"price":24.55},
{"isbn":"304553446-5","count":4,"price":44.27},
{"isbn":"237180483-5","count":220,"price":33.82},
{"isbn":"925461470-X","count":187,"price":53.19},
{"isbn":"036715922-8","count":313,"price":99.66},
{"isbn":"758311088-2","count":101,"price":92.41},
{"isbn":"418085723-5","count":481,"price":15.44},
{"isbn":"890617732-1","count":109,"price":26.41},
{"isbn":"920678239-8","count":135,"price":61.34},
{"isbn":"355975631-6","count":361,"price":33.66},
{"isbn":"482599132-7","count":76,"price":36.32},
{"isbn":"526356237-3","count":347,"price":12.48},
{"isbn":"379932293-0","count":153,"price":84.69},
{"isbn":"946494004-2","count":439,"price":95.91},
{"isbn":"453391730-5","count":41,"price":29.06},
{"isbn":"388352272-4","count":240,"price":19.68},
{"isbn":"400415070-1","count":269,"price":56.8},
{"isbn":"042969150-5","count":306,"price":61.63},
{"isbn":"905963362-8","count":286,"price":83.59},
{"isbn":"860751082-7","count":189,"price":59.21},
{"isbn":"102160027-X","count":257,"price":65.87},
{"isbn":"994907720-6","count":396,"price":76.34},
{"isbn":"115690658-X","count":287,"price":58.81},
{"isbn":"763224247-3","count":97,"price":48.78},
{"isbn":"800574084-0","count":176,"price":96.21},
{"isbn":"571731106-0","count":232,"price":26.54},
{"isbn":"545604092-1","count":245,"price":95.31},
{"isbn":"444833135-0","count":270,"price":19.43},
{"isbn":"424481884-7","count":331,"price":86.75},
{"isbn":"226326040-4","count":354,"price":59.33},
{"isbn":"888939470-6","count":38,"price":39.11},
{"isbn":"997510869-5","count":368,"price":19.65},
{"isbn":"232427455-8","count":227,"price":97.57},
{"isbn":"597339453-0","count":111,"price":22.98},
{"isbn":"653358501-0","count":270,"price":45.58},
{"isbn":"924258360-X","count":340,"price":30.03},
{"isbn":"385491650-7","count":208,"price":32.23},
{"isbn":"190403320-2","count":383,"price":38.53},
{"isbn":"786464745-6","count":161,"price":53.42},
{"isbn":"044333727-6","count":281,"price":23.73},
{"isbn":"276664553-5","count":148,"price":57.44},
{"isbn":"600556249-5","count":162,"price":46.65},
{"isbn":"823210883-5","count":141,"price":99.43},
{"isbn":"720722762-0","count":170,"price":19.53},
{"isbn":"147085070-2","count":215,"price":63.73},
{"isbn":"903988649-0","count":312,"price":96.51}]